poetry_demo_thomas_cleary/__init__.py
poetry_demo_thomas_cleary/cli.py
poetry_demo_thomas_cleary/data/data.txt
poetry_demo_thomas_cleary/example_functions.py
poetry_demo_thomas_cleary-1.0.3.dist-info/entry_points.txt
poetry_demo_thomas_cleary-1.0.3.dist-info/WHEEL
poetry_demo_thomas_cleary-1.0.3.dist-info/METADATA
poetry_demo_thomas_cleary-1.0.3.dist-info/RECORD
